lyric_scraper
