Metadata-Version: 2.1
Name: lyric-scraper
Version: 1.0.4
Summary: A tool to get lyrics for your favourite songs
Home-page: https://github.com/prakhar1965/lyric-scrapper
Author: Prakhar Omar
Author-email: praomar12@gmail.com
License: MIT
Platform: UNKNOWN
Classifier: Topic :: Software Development :: Build Tools
Classifier: License :: OSI Approved :: MIT License
Classifier: Programming Language :: Python :: 3
Classifier: Programming Language :: Python :: 3.4
Classifier: Programming Language :: Python :: 3.5
Classifier: Programming Language :: Python :: 3.6
